{"name":"@bbbbbbbbrandon 12-14-2021 09:16:55","description":"So much gwei so little time \\meem \\local","external_url":"https://raw.githubusercontent.com/meemproject/metadata/test/meem/32450bee-c656-44e4-9f04-8ffc3474fe71.json","meem_properties":{"root_token_uri":null,"root_token_address":null,"root_token_id":null,"root_token_metadata":null,"parent_token_uri":null,"parent_token_id":null,"parent_token_address":null,"parent_token_metadata":null},"image":"https://raw.githubusercontent.com/meemproject/metadata/test/meem/images/32450bee-c656-44e4-9f04-8ffc3474fe71.png","image_original":"https://raw.githubusercontent.com/meemproject/metadata/test/meem/images/32450bee-c656-44e4-9f04-8ffc3474fe71.png","extension_properties":{"tweet":{"id":"b94eefbd-8ad9-4f25-8dca-504ce5e01481","tweetId":"1470789910609252355","text":"So much gwei so little time \\meem \\local","username":"bbbbbbbbrandon","userProfileImageUrl":"https://abs.twimg.com/sticky/default_profile_images/default_profile_normal.png","updatedAt":"2021-12-14T16:17:06.204Z","createdAt":"2021-12-14T16:17:06.204Z","entities":{},"includes":{"users":[{"id":"1467976648054259715","name":"Brandon Minch","profile_image_url":"https://abs.twimg.com/sticky/default_profile_images/default_profile_normal.png","username":"bbbbbbbbrandon"}]}}}}